rhythmic_segments/__init__.py
rhythmic_segments/helpers.py
rhythmic_segments/meta.py
rhythmic_segments/patterns.py
rhythmic_segments/segments.py
rhythmic_segments-0.1.10.dist-info/METADATA
rhythmic_segments-0.1.10.dist-info/WHEEL
rhythmic_segments-0.1.10.dist-info/licenses/LICENSE
rhythmic_segments-0.1.10.dist-info/RECORD
