Metadata-Version: 2.4
Name: rhythmic_segments
Version: 0.1.10
Summary: Research code for basic Rhythmic Segment Analysis.
License-Expression: MIT
License-File: LICENSE
Keywords: rhythm,segments,music,analysis
Author: Bas Cornelissen
Author-email: mail@bascornelissen.nl
Requires-Python: >=3.11,<3.14
Classifier: Programming Language :: Python :: 3
Classifier: Programming Language :: Python :: 3.11
Classifier: Programming Language :: Python :: 3.12
Classifier: Programming Language :: Python :: 3.13
Requires-Dist: numpy (>=2.3.3,<3.0.0)
Requires-Dist: pandas (>=2.3.3,<3.0.0)
